mini_LiTOY/__init__.py
mini_LiTOY/__main__.py
mini_LiTOY/mini_LiTOY.py
mini_litoy-0.2.0.dist-info/licenses/COPYING
mini_litoy-0.2.0.dist-info/licenses/COPYING.LESSER
mini_litoy-0.2.0.dist-info/METADATA
mini_litoy-0.2.0.dist-info/WHEEL
mini_litoy-0.2.0.dist-info/entry_points.txt
mini_litoy-0.2.0.dist-info/top_level.txt
mini_litoy-0.2.0.dist-info/RECORD
