Metadata-Version: 2.4
Name: mini_LiTOY
Version: 0.2.0
Summary:  Minimalist LiTOY task sorting algorithm based on ELO scores
Home-page: https://github.com/thiswillbeyourgithub/mini_LiTOY
License: GPLv3
Keywords: tasks,sorting,ELO,scoring,organization,smart,tool,productivity,litoy,list,life,learning,optimization
Classifier: Programming Language :: Python :: 3
Classifier: License :: OSI Approved :: GNU General Public License v3 (GPLv3)
Classifier: Operating System :: OS Independent
Requires-Python: >=3.11
License-File: COPYING
License-File: COPYING.LESSER
Requires-Dist: fire>=0.6.0
Requires-Dist: typeguard>=0.4.3
Requires-Dist: rich>=13.7.1
Requires-Dist: prompt-toolkit>=3.0.40
Requires-Dist: platformdirs>=4.2.2
Requires-Dist: rtoml>=0.11.0
Requires-Dist: uuid6>=2024.7.10
Dynamic: classifier
Dynamic: description
Dynamic: description-content-type
Dynamic: home-page
Dynamic: keywords
Dynamic: license
Dynamic: license-file
Dynamic: requires-dist
Dynamic: requires-python
Dynamic: summary
